thrift_connector/__init__.py
thrift_connector/connection_pool.py
thrift_connector/hooks.py
thrift_connector/tornado.py
thrift_connector-0.23.dist-info/DESCRIPTION.rst
thrift_connector-0.23.dist-info/METADATA
thrift_connector-0.23.dist-info/RECORD
thrift_connector-0.23.dist-info/WHEEL
thrift_connector-0.23.dist-info/metadata.json
thrift_connector-0.23.dist-info/top_level.txt
