Metadata-Version: 2.0
Name: thrift-connector
Version: 0.23
Summary: Lib to connect to thrift services with pools
Home-page: https://github.com/eleme/thrift_connector
Author: Haochuan Guo
Author-email: guohaochuan@gmail.com
License: BSD
Keywords: thrift connection pool
Platform: UNKNOWN
